imtherapy/__init__.py
imtherapy/__main__.py
imtherapy/args.py
imtherapy/commands.py
imtherapy/defaults.py
imtherapy/envs.py
imtherapy/feature_selection/__init__.py
imtherapy/feature_selection/mlr3filters.py
imtherapy/feature_selection/mlr3fselect.py
imtherapy/feature_selection/use_all.py
imtherapy/feature_transform/__init__.py
imtherapy/feature_transform/direct.py
imtherapy/feature_transform/merge.py
imtherapy/machine_learning/__init__.py
imtherapy/machine_learning/_generic.py
imtherapy/machine_learning/glmnet.py
imtherapy/machine_learning/kknn.py
imtherapy/machine_learning/lda.py
imtherapy/machine_learning/log_reg.py
imtherapy/machine_learning/multinom.py
imtherapy/machine_learning/naive_bayes.py
imtherapy/machine_learning/nnet.py
imtherapy/machine_learning/qda.py
imtherapy/machine_learning/random_forest.py
imtherapy/machine_learning/svm.py
imtherapy/machine_learning/xgboost.py
imtherapy/modules.py
imtherapy/pipeline.py
imtherapy/processes.py
imtherapy/reports/FeatureFeatureRelationship.svx
imtherapy/reports/ImputeMissingData.svx
imtherapy/reports/PredictionMetrics.svx
imtherapy/reports/SurvivalAnalysis.svx
imtherapy/reports/UnivariateStatisticAnalysis.svx
imtherapy/scripts/FSMlr3FSelect.R
imtherapy/scripts/FSMlr3Filters.R
imtherapy/scripts/FeatureFeatureRelationship.R
imtherapy/scripts/ImputeMissingData.R
imtherapy/scripts/MachineLearning.R
imtherapy/scripts/MergeOtherFeatures.R
imtherapy/scripts/MergeTransformedFeatures.R
imtherapy/scripts/PredictionMetrics.R
imtherapy/scripts/SurvivalAnalysis.R
imtherapy/scripts/UnivariateStatisticAnalysis.R
imtherapy/scripts/utils.R
imtherapy/utils.py
imtherapy-0.0.0.dist-info/entry_points.txt
imtherapy-0.0.0.dist-info/WHEEL
imtherapy-0.0.0.dist-info/METADATA
imtherapy-0.0.0.dist-info/RECORD
